setup.py
python_runabove.egg-info/PKG-INFO
python_runabove.egg-info/SOURCES.txt
python_runabove.egg-info/dependency_links.txt
python_runabove.egg-info/requires.txt
python_runabove.egg-info/top_level.txt
runabove/__init__.py
runabove/account.py
runabove/base.py
runabove/client.py
runabove/exception.py
runabove/flavor.py
runabove/image.py
runabove/instance.py
runabove/region.py
runabove/ssh_key.py
runabove/storage.py
runabove/token.py
runabove/wrapper_api.py