Metadata-Version: 1.0
Name: python-runabove
Version: 1.3.0
Summary: RunAbove API Client Library
Home-page: https://www.runabove.com/
Author: RunAbove
Author-email: dev@runabove.com
License: MIT
Keywords: runabove api sdk
Platform: UNKNOWN
